examples/__init__.py
examples/example_hls4mlgru.py
examples/example_jedi_torch.py
examples/example_mnist.py
examples/example_mnist_torch.py
models/BuildModel.py
models/Models.py
models/TorchModels.py
models/__init__.py
models/get_3d.py
models/get_cifar10.py
models/get_mnist.py
models/get_topclass.py
nnlo/__init__.py
nnlo/data/__init__.py
nnlo/data/get_3d.py
nnlo/data/get_cifar10.py
nnlo/data/get_mnist.py
nnlo/data/get_topclass.py
nnlo/data/getdata.py
nnlo/driver/MPIGDriver.py
nnlo/driver/OptimizationDriver.py
nnlo/driver/TrainingDriver.py
nnlo/driver/__init__.py
nnlo/examples/__init__.py
nnlo/examples/example_cifar10.py
nnlo/examples/example_hls4mlgru.py
nnlo/examples/example_jedi_torch.py
nnlo/examples/example_mnist.py
nnlo/examples/example_mnist_torch.py
nnlo/models/BuildModel.py
nnlo/models/Models.py
nnlo/models/TorchModels.py
nnlo/models/__init__.py
nnlo/models/get_3d.py
nnlo/models/get_cifar10.py
nnlo/models/get_mnist.py
nnlo/models/get_topclass.py
nnlo/models/getdata.py
nnlo/models/model_cifar10_tf.py
nnlo/models/model_example_tf.py
nnlo/models/model_mnist_tf.py
nnlo/models/model_mnist_torch.py
nnlo/models/model_topclass_tf.py
nnlo/models/model_topclass_torch.py
nnlo/mpi/__init__.py
nnlo/mpi/manager.py
nnlo/mpi/process.py
nnlo/mpi/single_process.py
nnlo/optimize/__init__.py
nnlo/optimize/coordinator.py
nnlo/optimize/genetic_algorithm.py
nnlo/optimize/process_block.py
nnlo/train/GanModel.py
nnlo/train/__init__.py
nnlo/train/algo.py
nnlo/train/data.py
nnlo/train/model.py
nnlo/train/optimizer.py
nnlo/util/__init__.py
nnlo/util/count_epoch.py
nnlo/util/logger.py
nnlo/util/monitor.py
nnlo/util/timeline.py
nnlo/util/utils.py
nnlo-0.0.6.dist-info/METADATA
nnlo-0.0.6.dist-info/WHEEL
nnlo-0.0.6.dist-info/entry_points.txt
nnlo-0.0.6.dist-info/top_level.txt
nnlo-0.0.6.dist-info/RECORD
