Metadata-Version: 2.1
Name: nnlo
Version: 0.0.6
Summary: Distributed Machine Learning tool for High Performance Computing
Home-page: https://github.com/chnzhangrui/NNLO
Author: NNLO team
Author-email: rui.zhang@cern.ch
License: MIT
Download-URL: https://pypi.org/project/nnlo/
Keywords: Distributed Machine Learning,High Performance Computing,Hyperparameter optimisation
Platform: UNKNOWN
Requires-Dist: scikit-optimize
